{"filename":"/Users/brobert/Downloads/NibbleOneandTwoLiners(Complete)/Nibble One and Two Liners (1991, Part 1).dsk","size":143360,"device":"track/sector device","disks":[{"diskName":"DISK VOLUME #254","format":"DOS 3.3","freeSpace":80896,"usedSpace":62464,"logicalDiskNumber":0,"files":[{"locked":"*","type":"A","name":"HELLO","size":"378","sectors":"003","deleted":"","trackAndSectorList":"T18 S15","address":"A\u003d$0000"},{"locked":"*","type":"A","name":"SCREEN FALL","size":"186","sectors":"002","deleted":"","trackAndSectorList":"T19 S15","address":"A\u003d$0000"},{"locked":"*","type":"B","name":"PRINTER DUMP","size":"88","sectors":"002","deleted":"","trackAndSectorList":"T20 S15","address":"A\u003d$0300"},{"locked":"*","type":"B","name":"PRINTER DUMP ORIG","size":"72","sectors":"002","deleted":"","trackAndSectorList":"T21 S15","address":"A\u003d$0300"},{"locked":"*","type":"A","name":"PRINTER DUMP INSTR","size":"359","sectors":"003","deleted":"","trackAndSectorList":"T22 S15","address":"A\u003d$0000"},{"locked":"*","type":"A","name":"SHRINKER","size":"252","sectors":"002","deleted":"","trackAndSectorList":"T23 S15","address":"A\u003d$0000"},{"locked":"*","type":"A","name":"SHRINKER INSTRUCTIONS","size":"312","sectors":"003","deleted":"","trackAndSectorList":"T24 S15","address":"A\u003d$0000"},{"locked":"*","type":"A","name":"BRICKO","size":"416","sectors":"003","deleted":"","trackAndSectorList":"T24 S12","address":"A\u003d$0000"},{"locked":"*","type":"A","name":"DUEL","size":"396","sectors":"003","deleted":"","trackAndSectorList":"T24 S9","address":"A\u003d$0000"},{"locked":"*","type":"A","name":"DUEL INSTRUCTIONS","size":"124","sectors":"002","deleted":"","trackAndSectorList":"T25 S15","address":"A\u003d$0000"},{"locked":"*","type":"A","name":"PARADE","size":"332","sectors":"003","deleted":"","trackAndSectorList":"T24 S4","address":"A\u003d$0000"},{"locked":"*","type":"B","name":"IIGS COLOR","size":"99","sectors":"002","deleted":"","trackAndSectorList":"T25 S13","address":"A\u003d$0300"},{"locked":"*","type":"A","name":"IIGS COLOR INSTRUCTIONS","size":"414","sectors":"003","deleted":"","trackAndSectorList":"T26 S15","address":"A\u003d$0000"},{"locked":"*","type":"A","name":"FISH","size":"198","sectors":"002","deleted":"","trackAndSectorList":"T27 S15","address":"A\u003d$0000"},{"locked":"*","type":"A","name":"WIPEOUT","size":"110","sectors":"002","deleted":"","trackAndSectorList":"T28 S15","address":"A\u003d$0000"},{"locked":"*","type":"A","name":"SLIDEOUT","size":"107","sectors":"002","deleted":"","trackAndSectorList":"T29 S15","address":"A\u003d$0000"},{"locked":"*","type":"A","name":"SLIDEOUT INSTRUCTIONS","size":"270","sectors":"003","deleted":"","trackAndSectorList":"T30 S15","address":"A\u003d$0000"},{"locked":"*","type":"A","name":"IIGS MEMORY FREE","size":"282","sectors":"003","deleted":"","trackAndSectorList":"T31 S15","address":"A\u003d$0000"},{"locked":"*","type":"A","name":"NIBBLE SPECKLES","size":"285","sectors":"003","deleted":"","trackAndSectorList":"T32 S15","address":"A\u003d$0000"},{"locked":"*","type":"A","name":"SUBSTITUTION CODE","size":"246","sectors":"002","deleted":"","trackAndSectorList":"T33 S15","address":"A\u003d$0000"},{"locked":"*","type":"A","name":"PIG LATIN TRANSLATOR","size":"212","sectors":"002","deleted":"","trackAndSectorList":"T33 S13","address":"A\u003d$0000"},{"locked":"*","type":"A","name":"OH FUDGE","size":"396","sectors":"003","deleted":"","trackAndSectorList":"T34 S15","address":"A\u003d$0000"},{"locked":"*","type":"A","name":"OH FUDGE INSTRUCTIONS","size":"477","sectors":"003","deleted":"","trackAndSectorList":"T16 S15","address":"A\u003d$0000"},{"locked":"*","type":"A","name":"AMPER DEC-TO-HEX","size":"244","sectors":"002","deleted":"","trackAndSectorList":"T15 S15","address":"A\u003d$0000"},{"locked":"*","type":"A","name":"ML STRING","size":"412","sectors":"003","deleted":"","trackAndSectorList":"T14 S15","address":"A\u003d$0000"},{"locked":"*","type":"A","name":"ML STRING INSTRUCTIONS","size":"757","sectors":"004","deleted":"","trackAndSectorList":"T10 S15","address":"A\u003d$0000"},{"locked":"*","type":"A","name":"ADDRESSER","size":"387","sectors":"003","deleted":"","trackAndSectorList":"T10 S11","address":"A\u003d$0000"},{"locked":"*","type":"A","name":"ADDRESSER INSTRUCTIONS","size":"291","sectors":"003","deleted":"","trackAndSectorList":"T8 S15","address":"A\u003d$0000"},{"locked":"*","type":"A","name":"BORDERS","size":"155","sectors":"002","deleted":"","trackAndSectorList":"T10 S6","address":"A\u003d$0000"},{"locked":"*","type":"A","name":"SAUDI NIGHTS","size":"300","sectors":"003","deleted":"","trackAndSectorList":"T10 S4","address":"A\u003d$0000"},{"locked":"*","type":"A","name":"FRACTALS 1","size":"253","sectors":"002","deleted":"","trackAndSectorList":"T8 S12","address":"A\u003d$0000"},{"locked":"*","type":"B","name":"FRACTALS 1.PIC","size":"8,184","sectors":"033","deleted":"","trackAndSectorList":"T5 S15","address":"A\u003d$4000"},{"locked":"*","type":"A","name":"FRACTALS 2","size":"253","sectors":"002","deleted":"","trackAndSectorList":"T20 S13","address":"A\u003d$0000"},{"locked":"*","type":"B","name":"FRACTALS 2.PIC","size":"8,184","sectors":"033","deleted":"","trackAndSectorList":"T21 S13","address":"A\u003d$4000"},{"locked":"*","type":"A","name":"UP AND DOWN","size":"302","sectors":"003","deleted":"","trackAndSectorList":"T18 S12","address":"A\u003d$0000"},{"locked":"*","type":"A","name":"INTERFERENCE","size":"252","sectors":"002","deleted":"","trackAndSectorList":"T19 S13","address":"A\u003d$0000"},{"locked":"*","type":"A","name":"LITTLE DOGGY","size":"314","sectors":"003","deleted":"","trackAndSectorList":"T23 S7","address":"A\u003d$0000"},{"locked":"*","type":"B","name":"BUTTON USR","size":"37","sectors":"002","deleted":"","trackAndSectorList":"T23 S4","address":"A\u003d$0300"},{"locked":"*","type":"A","name":"BUTTON USR DEMO 1","size":"142","sectors":"002","deleted":"","trackAndSectorList":"T24 S6","address":"A\u003d$0000"},{"locked":"*","type":"A","name":"BUTTON USR DEMO 2","size":"166","sectors":"002","deleted":"","trackAndSectorList":"T25 S11","address":"A\u003d$0000"},{"locked":"*","type":"B","name":"AUX COPY","size":"62","sectors":"002","deleted":"","trackAndSectorList":"T25 S9","address":"A\u003d$0300"},{"locked":"*","type":"A","name":"AUX COPY INSTRUCTIONS","size":"560","sectors":"004","deleted":"","trackAndSectorList":"T26 S12","address":"A\u003d$0000"},{"locked":"*","type":"A","name":"HI WHEELER","size":"342","sectors":"003","deleted":"","trackAndSectorList":"T25 S5","address":"A\u003d$0000"},{"locked":"*","type":"A","name":"HI WHEELER INSTRUCTIONS","size":"100","sectors":"002","deleted":"","trackAndSectorList":"T27 S13","address":"A\u003d$0000"},{"locked":"*","type":"A","name":"IIGS TRANSWARP DETECTOR","size":"290","sectors":"003","deleted":"","trackAndSectorList":"T27 S11","address":"A\u003d$0000"},{"locked":"*","type":"A","name":"IIGS TRANSWARP DETECTOR INSTR","size":"242","sectors":"002","deleted":"","trackAndSectorList":"T29 S13","address":"A\u003d$0000"},{"locked":"*","type":"A","name":"IIGS FLASHER","size":"90","sectors":"002","deleted":"","trackAndSectorList":"T27 S6","address":"A\u003d$0000"}]}]}
